openapi_generator_cli/__init__.py
openapi_generator_cli/openapi-generator.jar
openapi_generator_cli/py.typed
openapi_generator_cli-7.19.0.dist-info/METADATA
openapi_generator_cli-7.19.0.dist-info/WHEEL
openapi_generator_cli-7.19.0.dist-info/entry_points.txt
openapi_generator_cli-7.19.0.dist-info/licenses/LICENSE
openapi_generator_cli-7.19.0.dist-info/RECORD
