Metadata-Version: 2.4
Name: openapi-generator-cli
Version: 7.19.0
Summary: CLI for openapi generator
Project-URL: Documentation, https://github.com/OpenAPITools/openapi-generator#3---usage
Project-URL: Homepage, https://openapi-generator.tech
Project-URL: Repository, https://github.com/OpenAPITools/openapi-generator
Author-email: OpenAPI Generator community <team@openapitools.org>
License: APACHE 2.0
License-File: LICENSE
Keywords: cli,generator,openapi
Classifier: License :: OSI Approved :: Apache Software License
Classifier: Programming Language :: Python
Classifier: Programming Language :: Python :: 3 :: Only
Classifier: Programming Language :: Python :: 3.10
Classifier: Programming Language :: Python :: 3.11
Classifier: Programming Language :: Python :: 3.12
Classifier: Programming Language :: Python :: 3.13
Classifier: Programming Language :: Python :: Implementation :: CPython
Classifier: Programming Language :: Python :: Implementation :: PyPy
Classifier: Typing :: Typed
Requires-Python: <4,>=3.10
Provides-Extra: jdk4py
Requires-Dist: jdk4py<22,>=21.0.4.1; (python_version >= '3.10') and extra == 'jdk4py'
